wirtual/agents/__init__.py
wirtual/agents/_exceptions.py
wirtual/agents/http_server.py
wirtual/agents/inference_runner.py
wirtual/agents/job.py
wirtual/agents/log.py
wirtual/agents/plugin.py
wirtual/agents/py.typed
wirtual/agents/types.py
wirtual/agents/vad.py
wirtual/agents/version.py
wirtual/agents/worker.py
wirtual/agents/cli/__init__.py
wirtual/agents/cli/cli.py
wirtual/agents/cli/log.py
wirtual/agents/cli/proto.py
wirtual/agents/cli/watcher.py
wirtual/agents/ipc/__init__.py
wirtual/agents/ipc/channel.py
wirtual/agents/ipc/inference_executor.py
wirtual/agents/ipc/inference_proc_executor.py
wirtual/agents/ipc/inference_proc_lazy_main.py
wirtual/agents/ipc/job_executor.py
wirtual/agents/ipc/job_proc_executor.py
wirtual/agents/ipc/job_proc_lazy_main.py
wirtual/agents/ipc/job_thread_executor.py
wirtual/agents/ipc/log_queue.py
wirtual/agents/ipc/proc_client.py
wirtual/agents/ipc/proc_pool.py
wirtual/agents/ipc/proto.py
wirtual/agents/ipc/supervised_proc.py
wirtual/agents/llm/__init__.py
wirtual/agents/llm/chat_context.py
wirtual/agents/llm/fallback_adapter.py
wirtual/agents/llm/function_context.py
wirtual/agents/llm/llm.py
wirtual/agents/metrics/__init__.py
wirtual/agents/metrics/base.py
wirtual/agents/metrics/usage_collector.py
wirtual/agents/metrics/utils.py
wirtual/agents/multimodal/__init__.py
wirtual/agents/multimodal/agent_playout.py
wirtual/agents/multimodal/multimodal_agent.py
wirtual/agents/pipeline/__init__.py
wirtual/agents/pipeline/agent_output.py
wirtual/agents/pipeline/agent_playout.py
wirtual/agents/pipeline/human_input.py
wirtual/agents/pipeline/log.py
wirtual/agents/pipeline/pipeline_agent.py
wirtual/agents/pipeline/plotter.py
wirtual/agents/pipeline/speech_handle.py
wirtual/agents/stt/__init__.py
wirtual/agents/stt/fallback_adapter.py
wirtual/agents/stt/stream_adapter.py
wirtual/agents/stt/stt.py
wirtual/agents/tokenize/__init__.py
wirtual/agents/tokenize/_basic_hyphenator.py
wirtual/agents/tokenize/_basic_paragraph.py
wirtual_agents-0.0.1.dist-info/METADATA
wirtual_agents-0.0.1.dist-info/WHEEL
wirtual_agents-0.0.1.dist-info/top_level.txt
wirtual_agents-0.0.1.dist-info/RECORD
