Metadata-Version: 2.1
Name: wirtual-agents
Version: 0.0.1
Summary: Wirtual Agents
Home-page: https://github.com/wirtualdev/wirtual-agents
License: Apache-2.0
Project-URL: Documentation, https://docs.wirtual.dev
Project-URL: Website, https://wirtual.dev/
Project-URL: Source, https://github.com/wirtualdev/wirtual-agents
Keywords: webrtc,realtime,audio,video,wirtual,agents,AI
Classifier: Intended Audience :: Developers
Classifier: License :: OSI Approved :: Apache Software License
Classifier: Topic :: Multimedia :: Sound/Audio
Classifier: Topic :: Multimedia :: Video
Classifier: Topic :: Scientific/Engineering :: Artificial Intelligence
Classifier: Programming Language :: Python :: 3
Classifier: Programming Language :: Python :: 3.9
Classifier: Programming Language :: Python :: 3.10
Classifier: Programming Language :: Python :: 3 :: Only
Requires-Python: >=3.9.0
Requires-Dist: click~=8.1
Requires-Dist: livekit>=0.18.1
Requires-Dist: livekit-api~=0.8
Requires-Dist: livekit-protocol~=0.7
Requires-Dist: protobuf>=3
Requires-Dist: pyjwt>=2.0.0
Requires-Dist: types-protobuf<5,>=4
Requires-Dist: watchfiles~=0.22
Requires-Dist: psutil~=5.9
Requires-Dist: aiohttp~=3.10
Requires-Dist: typing-extensions~=4.12
Requires-Dist: colorama; sys_platform == "win32"
Requires-Dist: aiodns~=3.2; sys_platform != "win32"
Provides-Extra: codecs
Requires-Dist: av>=12.0.0; extra == "codecs"
Requires-Dist: numpy>=1.26.0; extra == "codecs"
Provides-Extra: images
Requires-Dist: pillow>=10.3.0; extra == "images"
